Metadata-Version: 1.0
Name: mazic
Version: 0.2.0
Summary: contain some common preprocess function
Home-page: https://github.com/mazicwong/mazic
Author: mazicwong
Author-email: mazic@gmail.com
License: MIT Licence
Keywords: pip,usual lib,mazic,mazicwong
Platform: any
